{
    "attractions": {
        "url": "/attractions",
        "itemsattractions": [
            {
                "id": 1,
                "title": "Ce qui rend Tataouine unique",
                "images": {
                    "image1": "image/Samir lunaire.jpg",
                    "alt1": "visiteur"
                },
                "shortdescription": "Tataouine est une région fascinante du sud tunisien, célèbre pour ses ksour berbères, ses paysages désertiques et son lien avec Star Wars. Découvrez ce qui rend cette destination si unique.",
                "description": "Architecture troglodyte et ksour - Un patrimoine millénaire unique : Tataouine est mondialement célèbre pour ses ksour (pluriel de ksar), ces greniers fortifiés extraordinaires construits par les communautés berbères pour stocker et protéger leurs vivres, leurs récoltes et leurs biens précieux. Ces structures impressionnantes témoignent d'un génie architectural adapté aux contraintes du désert. Certains ksour, comme Ksar Ouled Soltane, Ksar Hadada ou Ksar Megabla, sont tout simplement magnifiques et remarquablement bien conservés. Leurs cellules de stockage (ghorfas) sont superposées sur plusieurs étages, parfois jusqu'à quatre niveaux, créant des structures vertigineuses qui donnent un aspect presque futuriste à ces édifices séculaires. Les murs épais en pierre et en pisé (terre crue) conservent naturellement la fraîcheur à l'intérieur, même pendant les canicules estivales. Chaque famille possédait sa propre ghorfa, identifiable par une marque distinctive. L'entretien et la défense du ksar se faisaient collectivement, renforçant les liens communautaires. Ces ksour n'étaient pas seulement des greniers, mais aussi des lieux de vie sociale, de réunion et de refuge en cas d'attaque. Aujourd'hui, ils constituent un témoignage exceptionnel de l'ingéniosité humaine face aux défis du climat saharien et représentent un patrimoine architectural unique au monde, classé pour certains au patrimoine mondial de l'UNESCO. Paysages lunaires et désertiques - Une beauté brute et saisissante : Les alentours de Tataouine offrent un décor naturel absolument spectaculaire et quasi irréel. Le paysage est fait de montagnes arides aux formes sculptées par l'érosion millénaire, de plateaux rocheux qui s'étendent à l'infini, de vallées asséchées (oueds) qui ne voient l'eau que quelques jours par an, et de formations géologiques étonnantes. C'est un terrain presque surnaturel, d'une beauté austère et puissante, parfait pour l'aventure, la randonnée, le trekking et la contemplation méditative. Les couleurs changent au fil de la journée : ocre au lever du soleil, blanc éclatant à midi, rouge cuivré au coucher du soleil. Le silence absolu du désert, interrompu seulement par le vent, offre une expérience de connexion profonde avec la nature. Les amateurs de photographie y trouvent des paysages d'une beauté exceptionnelle, dignes des plus grands déserts du monde. Cette région est également réputée pour son ciel étoilé extraordinaire, sans pollution lumineuse, offrant des nuits magiques sous la Voie lactée. L'inspiration pour Star Wars - Quand la réalité dépasse la fiction : Tataouine a directement et officiellement inspiré George Lucas pour nommer la planète désertique Tatooine dans la saga Star Wars. Le réalisateur a découvert cette région lors de repérages dans les années 1970 et a été immédiatement fasciné par ces paysages lunaires et ces architectures futuristes des ksour. Plusieurs scènes emblématiques de la saga ont même été tournées dans la région de Tataouine et ses environs : notamment à Ksar Ouled Soltane, Ksar Hadada, Matmata et dans le désert du Grand Erg Oriental. Les décors de la maison de Luke Skywalker, du quartier des esclaves d'Anakin, et de la cantina de Mos Eisley sont directement inspirés ou filmés dans ces lieux authentiques. Aujourd'hui, Tataouine est devenue un véritable lieu de pèlerinage pour les fans de science-fiction du monde entier, qui viennent marcher sur les traces de leurs héros préférés et découvrir les décors réels qui ont servi à créer l'univers mythique de Star Wars. Des tours organisés permettent de visiter tous les sites de tournage de la région. Culture authentique et traditions berbères vivantes : Contrairement aux zones touristiques très fréquentées et souvent standardisées du nord de la Tunisie, Tataouine reste encore profondément et authentiquement ancrée dans ses traditions ancestrales berbères et sahariennes. L'artisanat traditionnel y est toujours pratiqué : tissage de tapis et kilims aux motifs géométriques berbères, poterie faite à la main selon des techniques millénaires, vannerie en feuilles de palmier, bijouterie en argent avec des symboles ancestraux. La gastronomie locale est savoureuse et typique : couscous berbère aux légumes et viande d'agneau, pain traditionnel cuit au four en terre, pâtisseries au miel et aux dattes, thé à la menthe parfumé. Les habitants portent encore parfois les tenues traditionnelles lors des fêtes et cérémonies : robes brodées, bijoux en argent massif, voiles colorés. Les mariages traditionnels berbères sont de véritables spectacles culturels, avec danses, chants et rituels ancestraux qui durent plusieurs jours. L'hospitalité légendaire des habitants du Sud tunisien reste intacte : vous serez accueilli avec chaleur et générosité. Il y a une vraie authenticité dans les rencontres et les échanges, loin du tourisme commercial. Les villages troglodytes - Des siècles d'adaptation ingénieuse : Des endroits exceptionnels comme Chenini, Douiret, Guermessa ou encore Toujane, tous perchés de manière spectaculaire sur des collines et des crêtes rocheuses, montrent des habitations impressionnantes creusées directement dans la roche calcaire ou volcanique. Ces villages troglodytiques racontent des siècles d'histoire humaine et témoignent d'une adaptation remarquable et ingénieuse aux conditions climatiques extrêmes du Sud tunisien : chaleur torride en été (jusqu'à 50°C), froid en hiver, sécheresse quasi permanente, vents violents. Les habitations creusées dans la roche offrent une isolation thermique naturelle exceptionnelle : fraîcheur en été, chaleur en hiver, sans aucune énergie artificielle. L'architecture mélange grottes naturelles aménagées et constructions en pierre, créant un ensemble harmonieux intégré au paysage. Ces villages constituent un patrimoine architectural et culturel unique, témoignant de la résilience et de la créativité des populations berbères face aux défis du désert. Aujourd'hui, certains habitants maintiennent ces traditions, tandis que d'autres ont migré vers des villages modernes en contrebas, laissant ces lieux chargés d'histoire et d'émotion. Le rythme de vie paisible - Un autre rapport au temps : À Tataouine et dans sa région, le temps semble vraiment ralentir et prendre une autre dimension. Le rythme de vie suit encore largement celui du soleil, des saisons et des traditions ancestrales. Les journées s'écoulent paisiblement, ponctuées par les prières, les moments de convivialité autour du thé à la menthe, les siestes à l'ombre pendant les heures chaudes, et les longues soirées sous les étoiles. C'est un endroit parfait et idéal pour ceux qui cherchent à échapper aux circuits touristiques classiques et standardisés, à se déconnecter du stress de la vie moderne, à ralentir leur rythme effréné, et à ressentir un autre rapport au temps et à l'espace. Ici, vous apprendrez à apprécier la simplicité, le silence, la contemplation, et les vraies rencontres humaines. C'est une destination privilégiée pour une introspection personnelle, une reconnexion avec l'essentiel, et une expérience de voyage authentique et transformatrice, loin du tourisme de masse."
            },
            {
                "id": 2,
                "title": "Trois attractions incontournables",
                "images": {
                    "image1": "image/20250514_160823.jpg",
                    "alt1": "visiteur"
                },
                "shortdescription": "Découvrez les trois sites emblématiques de Tataouine : Chenini, Ksar Ouled Soltane et Douiret. Ces lieux chargés d'histoire vous transportent dans l'univers fascinant des ksour berbères.",
                "description": "Chenini - Le village de l'âme berbère : Pourquoi c'est incontournable ? Chenini, c'est l'âme de Tataouine. Ce vieux village berbère est à moitié troglodyte : certaines maisons sont creusées directement dans la roche calcaire de la montagne. L'endroit est suspendu à flanc de colline, offrant une vue panoramique incroyable sur toute la vallée désertique qui s'étend à perte de vue. Vous sentez vraiment l'histoire partout : le village date de plusieurs siècles et il est encore habité par quelques familles qui perpétuent les traditions ancestrales. L'architecture unique mélange habitations troglodytiques et constructions traditionnelles en pierre, créant un ensemble architectural fascinant. Les maisons s'empilent les unes sur les autres, reliées par des escaliers escarpés taillés dans la roche. Ce lieu offre une expérience authentique de la vie berbère traditionnelle, loin du tourisme de masse. À ne pas manquer : La mosquée des Sept Dormants (Sidi Abdelkader), lieu de pèlerinage important, les ruelles escarpées qui serpentent entre les habitations, les ghorfas (cellules de stockage) encore visibles, et le coucher de soleil depuis le sommet du village qui embrase toute la vallée. Ksar Ouled Soltane - Le joyau architectural du désert : Pourquoi c'est incontournable ? C'est l'un des ksour les mieux conservés et les plus impressionnants de toute la région du Sud tunisien. Un ksar est un grenier collectif fortifié où les habitants berbères stockaient grains, olives, huile et marchandises précieuses pour se protéger des pillards et des invasions. Ksar Ouled Soltane est tout simplement spectaculaire avec ses cellules (ghorfas) empilées sur quatre niveaux en hauteur, formant un labyrinthe vertical de petites pièces voûtées en pierre ocre. L'ensemble forme une cour intérieure entourée de ces structures impressionnantes qui semblent défier les lois de la gravité. Chaque famille possédait sa propre ghorfa, accessible par des escaliers abrupts. L'architecture témoigne d'un ingénieux système de construction adapté au climat aride : les murs épais conservent la fraîcheur et protègent les denrées stockées. Le lieu dégage une atmosphère unique, presque mystique, renforcée par le silence du désert environnant. Fun fact : Certaines scènes iconiques de Star Wars Episode I - La Menace Fantôme y ont été tournées. C'est notamment ici que se trouve le quartier des esclaves où vivait le jeune Anakin Skywalker ! Les fans de la saga viennent du monde entier pour marcher sur les traces de George Lucas et revivre la magie du film dans ce décor naturel extraordinaire. Douiret - Le village oublié du temps : Pourquoi c'est incontournable ? Moins touristique et moins fréquenté que Chenini, Douiret est un ancien village semi-troglodyte encore plus brut, plus sauvage et plus authentique. C'est un véritable voyage dans le temps. Se promener là-bas, c'est comme marcher dans un décor oublié du monde moderne : vieilles maisons en ruine témoignant d'une vie passée, anciennes mosquées aux minarets blancs qui dominent le paysage, greniers fortifiés abandonnés, sentiers de pierre battus par des générations de Berbères. Le village est perché sur une crête rocheuse escarpée, offrant une vue imprenable sur la vallée et le nouveau village moderne en contrebas. L'atmosphère y est particulièrement émouvante : on ressent la présence des anciens habitants, le poids de l'histoire et la beauté mélancolique de ces constructions progressivement abandonnées au profit du village moderne. Les maisons troglodytiques creusées dans la falaise sont encore bien visibles, certaines conservant leurs portes en bois sculpté. L'ensemble architectural témoigne de l'adaptation remarquable des populations berbères aux conditions climatiques extrêmes du Sud tunisien. Bonus : Vous pouvez facilement faire une petite randonnée pédestre autour du village pour découvrir de superbes panoramas désertiques, explorer les environs rocailleux, et profiter du silence absolu du désert. Le sentier qui fait le tour du village offre des points de vue exceptionnels pour la photographie, surtout en fin d'après-midi quand la lumière dorée du soleil illumine les pierres ocres. C'est l'endroit idéal pour les amateurs de randonnée, de photographie et de contemplation paisible loin de l'agitation touristique."
            },
            {
                "id": 3,
                "title": "Immersion culturelle à Tataouine",
                "images": {
                    "image1": "image/immersion.jpg",
                    "alt1": "Immersion culturelle"
                },
                "shortdescription": "Vivez une expérience authentique au cœur de la culture berbère : rencontrez les habitants, partagez un repas traditionnel, découvrez l'artisanat local et participez à la vie du désert.",
                "description": "Passer du temps avec les habitants : Ne vous contentez pas d'une visite rapide, prenez le temps de discuter avec les gens du coin, surtout à Chenini, Douiret ou dans les petits marchés de Tataouine ville. Beaucoup de Berbères locaux sont très accueillants et adorent raconter l'histoire de leurs villages, parfois autour d'un thé à la menthe fait maison. Ces moments d'échange authentique vous permettront de comprendre leur mode de vie, leurs traditions et leur attachement profond à cette terre aride. Participer à un repas traditionnel : Essayez de manger dans des petites maisons d'hôtes ou chez l'habitant. Ils vous proposeront souvent des plats traditionnels comme le couscous berbère (plus rustique et parfumé que ce qu'on trouve ailleurs), la chorba (soupe épicée), le pain cuit dans la cendre (un vrai régal). Vous pouvez aussi apprendre comment ils préparent leur pain ou leurs pâtisseries locales (comme les makroudhs). Ces repas partagés sont des moments privilégiés de convivialité et de découverte culinaire. S'initier à l'artisanat local : Tataouine est réputée pour ses tapis berbères faits main aux motifs géométriques traditionnels et ses poteries artisanales. Il y a parfois des ateliers où vous pouvez apprendre à tisser ou à fabriquer un petit objet traditionnel. C'est une excellente façon de comprendre les savoir-faire ancestraux transmis de génération en génération et de repartir avec un souvenir unique fait de vos propres mains. Faire une balade avec un guide local : Certains anciens du village proposent des randonnées guidées (parfois même à dos de dromadaire). C'est l'occasion d'entendre les légendes du désert, les histoires de batailles anciennes, ou les coutumes locales expliquées par ceux qui vivent ici depuis toujours. Ces guides connaissent chaque recoin du territoire et vous feront découvrir des lieux secrets inaccessibles aux touristes ordinaires. Assister à une fête ou un événement traditionnel : Si vous avez de la chance, vous pourrez assister à des mariages berbères ou des petits festivals locaux où vous verrez des danses traditionnelles (comme la Dabka) ou écouterez de la musique locale (avec des tambours bendir et des chants ancestraux). Même sans événement particulier, certains cafés traditionnels accueillent des musiciens en soirée pour des concerts improvisés qui créent une ambiance magique sous les étoiles du désert. Ces expériences d'immersion culturelle transformeront votre voyage en une véritable aventure humaine et authentique."
            },
            {
                "id": 4,
                "title": "Conseils pour une visite optimale",
                "images": {
                    "image1": "image/20250516_133938.jpg",
                    "alt1": "Conseils voyage"
                },
                "shortdescription": "Préparez votre aventure à Tataouine avec nos conseils pratiques : meilleure période pour visiter, équipements indispensables, respect des coutumes locales et sécurité dans le désert.",
                "description": "Meilleurs moments pour visiter - Saison idéale : La meilleure période pour visiter Tataouine s'étend de mars à mai au printemps, ou d'octobre à novembre en automne. Durant ces mois, le climat est particulièrement agréable avec des températures douces pendant la journée et une fraîcheur bienvenue la nuit. Le printemps offre en plus l'avantage de voir le désert se parer de couleurs vives après les rares pluies hivernales, avec parfois des fleurs sauvages qui émergent du sable. L'automne permet de profiter de lumières exceptionnelles pour la photographie avec des ciels particulièrement clairs. Il est fortement recommandé d'éviter la période estivale entre juin et août où les températures peuvent atteindre 45 degrés Celsius, rendant toute randonnée ou visite prolongée extrêmement pénible et potentiellement dangereuse. L'hiver entre décembre et février peut être étonnamment froid la nuit avec des températures proches de zéro degré. Meilleurs moments pour visiter - Moments de la journée : Le matin tôt, entre 7 heures et 10 heures, est le moment idéal pour explorer les villages et les ksour. La lumière est douce et dorée, parfaite pour la photographie, et la chaleur n'est pas encore accablante. C'est aussi le moment où vous croiserez les habitants qui commencent leur journée, offrant des opportunités d'échanges authentiques. La fin d'après-midi, à partir de 17 heures jusqu'au coucher du soleil, offre une lumière magique sur les montagnes et les ksour. Les pierres ocres des constructions prennent des teintes dorées puis rougeoyantes absolument spectaculaires. C'est le moment préféré des photographes professionnels. Le milieu de journée entre 12 heures et 16 heures est à éviter pour les visites extérieures, préférez ce moment pour vous reposer à l'ombre, déjeuner tranquillement ou visiter des espaces intérieurs comme les musées ou les ateliers d'artisanat. Éléments à ne surtout pas manquer - À Chenini : Montez absolument jusqu'à la mosquée blanche des Sept Dormants qui domine tout le village. La montée peut être un peu rude mais la vue panoramique sur toute la vallée désertique en vaut largement l'effort. De là-haut, vous comprendrez l'implantation stratégique du village et admirerez un panorama à couper le souffle. Prenez le temps de flâner dans les ruelles abandonnées du vieux village, entre les vieilles portes en bois sculpté et les maisons troglodytes. Chaque recoin raconte une histoire et offre des perspectives photographiques uniques. Explorez les terrasses qui offrent des points de vue sur les montagnes environnantes. Éléments à ne surtout pas manquer - À Ksar Ouled Soltane : N'hésitez pas à grimper dans les étages supérieurs des ghorfas pour avoir une vue d'ensemble impressionnante sur toute l'architecture du ksar. Les escaliers en pierre sont parfois étroits et raides mais l'effort en vaut la peine. Cherchez les cellules de stockage en forme d'alvéoles qui sont particulièrement photogéniques avec leurs voûtes en berceau et leurs portes anciennes. Le jeu d'ombres et de lumières à travers les ouvertures crée des effets visuels extraordinaires. Visitez les deux cours intérieures du ksar pour comprendre l'organisation communautaire de ces greniers fortifiés. Éléments à ne surtout pas manquer - À Douiret : Visitez les anciennes mosquées creusées directement dans la roche, témoignages remarquables de l'ingéniosité architecturale berbère. Certaines ont conservé leurs mihrabs sculptés et leurs plafonds voûtés. Baladez-vous autour du village pour découvrir les anciens puits et citernes berbères qui permettaient la survie dans ce milieu aride. Ces installations hydrauliques ancestrales sont de véritables prouesses techniques. Faites le tour complet du village en suivant les sentiers de crête pour profiter de panoramas exceptionnels sur la vallée et le nouveau village moderne en contrebas. Conseils pratiques - Équipement indispensable : Prévoyez de bonnes chaussures de marche confortables et déjà rodées, même pour les visites de villages car les chemins sont souvent escarpés, caillouteux et les escaliers nombreux. Des chaussures montantes offrant un bon maintien de la cheville sont recommandées. Ayez toujours une bouteille d'eau sur vous, au minimum un litre et demi par personne. Même au printemps ou en automne, le soleil du désert déshydrate rapidement. Renouvelez votre stock d'eau dès que possible. La protection solaire est absolument obligatoire : casquette ou chapeau à large bord, lunettes de soleil avec protection UV, crème solaire indice 50 minimum à renouveler toutes les deux heures. Un foulard léger peut aussi protéger la nuque. Préparez votre appareil photo ou smartphone avec suffisamment de mémoire car les paysages sont extraordinairement photogéniques et vous prendrez beaucoup plus de photos que prévu. Une batterie externe est recommandée. Conseils pratiques - Respect des lieux et des habitants : Certains sites sont encore utilisés par les habitants locaux, particulièrement les mosquées et certaines habitations. Il est impératif de s'habiller de manière respectueuse en couvrant épaules et jambes dans les villages berbères traditionnels. Pour les femmes, un foulard léger peut être utile pour couvrir les épaules ou la tête si nécessaire. Demandez toujours la permission avant de photographier les habitants, surtout les femmes et les enfants. Beaucoup accepteront avec plaisir mais certains peuvent refuser pour des raisons religieuses ou personnelles. Respectez ces choix sans insister. Ne pénétrez pas dans les propriétés privées sans y avoir été invité. Même si une maison semble abandonnée, elle appartient toujours à quelqu'un. Si vous achetez de l'artisanat local, négociez avec respect et bonne humeur. Le marchandage fait partie de la culture mais doit rester courtois. Pensez que les prix demandés sont souvent déjà très raisonnables pour un travail artisanal de qualité. Astuce bonus - Vivre une expérience unique : Si vous voulez vivre un moment vraiment inoubliable et authentique, planifiez de passer une nuit sur place dans une maison d'hôtes traditionnelle à Chenini ou Douiret. Le ciel étoilé du désert est absolument époustouflant car il n'y a pratiquement aucune pollution lumineuse. Vous verrez la Voie lactée dans toute sa splendeur, des milliers d'étoiles visibles à l'oeil nu, et par chance peut-être même des étoiles filantes. Le silence profond du désert la nuit est une expérience en soi, presque méditative. Vous n'entendrez que le vent léger et parfois le cri lointain d'un animal nocturne. Ce calme absolu, si rare dans notre monde moderne, laisse une impression durable. Les levers et couchers de soleil vus depuis ces villages perchés offrent des spectacles de couleurs incomparables. C'est l'occasion de vraiment vous déconnecter du monde moderne et de vous reconnecter avec l'essentiel."
            }
        ]
    }
}
